webactogram/__init__.py
webactogram/webactogram.py
webactogram-0.4.2.dist-info/LICENSE
webactogram-0.4.2.dist-info/METADATA
webactogram-0.4.2.dist-info/WHEEL
webactogram-0.4.2.dist-info/entry_points.txt
webactogram-0.4.2.dist-info/top_level.txt
webactogram-0.4.2.dist-info/RECORD
