Metadata-Version: 2.1
Name: webactogram
Version: 0.4.2
Summary: Actogram from browsers history, may help to screen sleep-wake patterns & disorders!
Author-email: "Barrett F. Davis" <barrettfdavis@gmail.com>, Stephen Karl Larroque <LRQ3000@gmail.com>
Maintainer-email: Stephen Karl Larroque <LRQ3000@gmail.com>
License: MIT License
Project-URL: Homepage, https://github.com/Circadiaware/webactogram
Project-URL: Documentation, https://github.com/Circadiaware/webactogram/blob/master/README.md
Project-URL: Source, https://github.com/Circadiaware/webactogram
Project-URL: Tracker, https://github.com/Circadiaware/webactogram/issues
Project-URL: Download, https://github.com/Circadiaware/webactogram/releases
Project-URL: Changelog, https://allmychanges.com/p/python/webactogram/
Keywords: actogram,sleep,pattern,activity,graph,browser,internet,online,actigraphy
Classifier: Development Status :: 4 - Beta
Classifier: License :: OSI Approved :: MIT License
Classifier: Environment :: Console
Classifier: Operating System :: MacOS :: MacOS X
Classifier: Operating System :: Microsoft :: Windows
Classifier: Operating System :: POSIX
Classifier: Operating System :: POSIX :: Linux
Classifier: Intended Audience :: End Users/Desktop
Classifier: Intended Audience :: Healthcare Industry
Classifier: Intended Audience :: Science/Research
Classifier: Programming Language :: Python
Classifier: Programming Language :: Python :: 3
Classifier: Programming Language :: Python :: 3.7
Classifier: Programming Language :: Python :: 3.8
Classifier: Programming Language :: Python :: 3.9
Classifier: Programming Language :: Python :: 3.10
Classifier: Programming Language :: Python :: 3.11
Classifier: Programming Language :: Python :: 3.12
Classifier: Programming Language :: Python :: Implementation :: PyPy
Classifier: Topic :: Internet :: Log Analysis
Classifier: Topic :: Internet :: WWW/HTTP :: Browsers
Classifier: Topic :: Scientific/Engineering :: Bio-Informatics
Classifier: Topic :: Scientific/Engineering :: Medical Science Apps.
Requires-Python: >=3.7
License-File: LICENSE
Requires-Dist: matplotlib >=3.3.4
Requires-Dist: numpy >=1.21.0
Requires-Dist: pandas >=1.3.4
Requires-Dist: scipy >=1.6.1
Requires-Dist: browser-history
Provides-Extra: test
Requires-Dist: pytest ; extra == 'test'
Requires-Dist: pytest-cov ; extra == 'test'
Provides-Extra: testmeta
Requires-Dist: build ; extra == 'testmeta'
Requires-Dist: twine ; extra == 'testmeta'
Requires-Dist: validate-pyproject ; extra == 'testmeta'
